connecteam_api_sdk/__init__.py
connecteam_api_sdk/_base_client.py
connecteam_api_sdk/_client.py
connecteam_api_sdk/_compat.py
connecteam_api_sdk/_constants.py
connecteam_api_sdk/_exceptions.py
connecteam_api_sdk/_files.py
connecteam_api_sdk/_models.py
connecteam_api_sdk/_qs.py
connecteam_api_sdk/_resource.py
connecteam_api_sdk/_response.py
connecteam_api_sdk/_streaming.py
connecteam_api_sdk/_types.py
connecteam_api_sdk/_version.py
connecteam_api_sdk/py.typed
connecteam_api_sdk/_utils/__init__.py
connecteam_api_sdk/_utils/_logs.py
connecteam_api_sdk/_utils/_proxy.py
connecteam_api_sdk/_utils/_reflection.py
connecteam_api_sdk/_utils/_resources_proxy.py
connecteam_api_sdk/_utils/_streams.py
connecteam_api_sdk/_utils/_sync.py
connecteam_api_sdk/_utils/_transform.py
connecteam_api_sdk/_utils/_typing.py
connecteam_api_sdk/_utils/_utils.py
connecteam_api_sdk/lib/.keep
connecteam_api_sdk/resources/__init__.py
connecteam_api_sdk/resources/me.py
connecteam_api_sdk/resources/attachments/__init__.py
connecteam_api_sdk/resources/attachments/attachments.py
connecteam_api_sdk/resources/attachments/v1/__init__.py
connecteam_api_sdk/resources/attachments/v1/files.py
connecteam_api_sdk/resources/attachments/v1/v1.py
connecteam_api_sdk/resources/chat/__init__.py
connecteam_api_sdk/resources/chat/chat.py
connecteam_api_sdk/resources/chat/v1/__init__.py
connecteam_api_sdk/resources/chat/v1/conversations.py
connecteam_api_sdk/resources/chat/v1/v1.py
connecteam_api_sdk/resources/daily_info/__init__.py
connecteam_api_sdk/resources/daily_info/daily_info.py
connecteam_api_sdk/resources/daily_info/v1/__init__.py
connecteam_api_sdk/resources/daily_info/v1/daily_note.py
connecteam_api_sdk/resources/daily_info/v1/v1.py
connecteam_api_sdk/resources/forms/__init__.py
connecteam_api_sdk/resources/forms/forms.py
connecteam_api_sdk/resources/forms/v1/__init__.py
connecteam_api_sdk/resources/forms/v1/v1.py
connecteam_api_sdk/resources/forms/v1/forms/__init__.py
connecteam_api_sdk-0.0.1a1.dist-info/METADATA
connecteam_api_sdk-0.0.1a1.dist-info/WHEEL
connecteam_api_sdk-0.0.1a1.dist-info/licenses/LICENSE
connecteam_api_sdk-0.0.1a1.dist-info/RECORD
